setup.py
bin/triform2
tests/__init__.py
tests/conftest.py
triform/__init__.py
triform/chromosome.py
triform/compute_fdr.py
triform/create_bigwig.py
triform/exclude_redundant_peaks.py
triform/find_peaks.py
triform/helper_functions.py
triform/init.py
triform/make_treatment_control_same_length.py
triform/run_triform.py
triform/version.py
triform/R/__init__.py
triform/config/__init__.py
triform/config/genomes.py
triform/config/logging_settings.py
triform/preprocess/__init__.py
triform/preprocess/bed_to_chromosome_dfs.py
triform/preprocess/make_chromosome_cover_files.py
triform/preprocess/make_ranged_data.py
triform/preprocess/preprocess.py
triform/scripts/__init__.py
triform/scripts/bioconda_setup.py
triform/scripts/chromsizes/dm3.chromsizes
triform/scripts/chromsizes/dm6.chromsizes
triform/scripts/chromsizes/hg19.chromsizes
triform/scripts/chromsizes/hg38.chromsizes
triform/scripts/chromsizes/mm10.chromsizes
triform/scripts/chromsizes/mm9.chromsizes
triform2.egg-info/PKG-INFO
triform2.egg-info/SOURCES.txt
triform2.egg-info/dependency_links.txt
triform2.egg-info/requires.txt
triform2.egg-info/top_level.txt