Metadata-Version: 1.1
Name: triform2
Version: 0.0.3
Summary: Improved sensitivity, specificity and control of false discovery rates in ChIP-Seq peak finding.
Home-page: http://github.com/endrebak/triform2
Author: Endre Bakken Stovner
Author-email: endrebak85@gmail.com
License: ['MIT']
Keywords: ChIP-Seq
Platform: UNKNOWN
Classifier: Programming Language :: Python :: 2.7
Classifier: Programming Language :: Python :: 3
Classifier: Development Status :: 2 - Pre-Alpha
Classifier: Environment :: Other Environment
Classifier: Intended Audience :: Developers
Classifier: Intended Audience :: Science/Research
Classifier: License :: OSI Approved :: GNU General Public License v3 (GPLv3)
Classifier: Operating System :: POSIX :: Linux
Classifier: Operating System :: MacOS :: MacOS X
Classifier: Topic :: Scientific/Engineering
